README
setup.py
mandy/__init__.py
mandy/mandy.py
mandy.egg-info/PKG-INFO
mandy.egg-info/SOURCES.txt
mandy.egg-info/dependency_links.txt
mandy.egg-info/requires.txt
mandy.egg-info/top_level.txt