Metadata-Version: 1.0
Name: mandy
Version: 0.1.4
Summary: a terse command-line options parser
Home-page: http://pypi.python.org/pypi/mandy/
Author: Tim Cuthbertson
Author-email: tim3d.junk+mandy@gmail.com
License: BSD
Keywords: optparse option parsing command commandline simple
Platform: UNKNOWN
Classifier: License :: OSI Approved :: BSD License
Classifier: Programming Language :: Python
Classifier: Development Status :: 4 - Beta
Classifier: Intended Audience :: Developers
Classifier: Topic :: Software Development :: Libraries :: Python Modules
